wraps_futures_core/__init__.py
wraps_futures_core/future.py
wraps_futures_core/py.typed
wraps_futures_core/reawaitable.py
wraps_futures_core/typing.py
wraps_futures_core-0.1.1.dist-info/METADATA
wraps_futures_core-0.1.1.dist-info/WHEEL
wraps_futures_core-0.1.1.dist-info/licenses/LICENSE
wraps_futures_core-0.1.1.dist-info/RECORD
